marchitect/__init__.py
marchitect/prefab.py
marchitect/py.typed
marchitect/site_plan.py
marchitect/util.py
marchitect/whiteprint.py
test/__init__.py
test/test_basic.py
marchitect-0.9.dist-info/WHEEL
marchitect-0.9.dist-info/METADATA
marchitect-0.9.dist-info/licenses/LICENSE-MIT
marchitect-0.9.dist-info/RECORD
