Metadata-Version: 2.1
Name: marchitect
Version: 0.9
Summary: Machine architect for software deployment.
License: MIT
Author-email: Ken Elkabany <ken@elkabany.com>
Requires-Python: >=3.9,<4.0
Classifier: Development Status :: 5 - Production/Stable
Classifier: Intended Audience :: Developers
Classifier: License :: OSI Approved :: MIT License
Classifier: Natural Language :: English
Classifier: Operating System :: POSIX :: Linux
Classifier: Programming Language :: Python :: 3
Classifier: Programming Language :: Python :: 3.6
Classifier: Programming Language :: Python :: 3.7
Classifier: Topic :: System :: Installation/Setup
Classifier: Topic :: System :: Systems Administration
Requires-Dist: jinja2>=2.10
Requires-Dist: schema>=0.7.0
Requires-Dist: ssh2-python312>=0.1.1
Project-URL: repository, https://www.github.com/braincore/marchitect
